copper/__init__.py
copper/chiller.py
copper/cli.py
copper/constants.py
copper/curves.py
copper/data/chiller_curves.json
copper/data/equipment_references.json
copper/data/schema/copper.chiller.action.schema.json
copper/data/schema/copper.chiller.generate_set_of_curves.schema.json
copper/data/schema/copper.chiller.schema.json
copper/data/schema/copper.schema.json
copper/data/schema/copper.unitarydirectexpansion.action.schema.json
copper/data/schema/copper.unitarydirectexpansion.generate_set_of_curves.schema.json
copper/data/schema/copper.unitarydirectexpansion.schema.json
copper/data/unitarydirectexpansion_curves.json
copper/equipment.py
copper/generator.py
copper/helpers.py
copper/i_o_process.py
copper/library.py
copper/schema.py
copper/unitarydirectexpansion.py
copper/units.py
copper_bem-0.2.9.dist-info/METADATA
copper_bem-0.2.9.dist-info/WHEEL
copper_bem-0.2.9.dist-info/entry_points.txt
copper_bem-0.2.9.dist-info/licenses/LICENSE.md
copper_bem-0.2.9.dist-info/RECORD
