Metadata-Version: 2.4
Name: copper-bem
Version: 0.2.9
Summary: Performance curve generator for building energy simulation
License-File: LICENSE.md
Author: Lerond, Jeremy
Author-email: jeremy.lerond@pnnl.gov
Requires-Python: >=3.10,<4.0
Classifier: Programming Language :: Python :: 3
Classifier: Programming Language :: Python :: 3.10
Classifier: Programming Language :: Python :: 3.11
Classifier: Programming Language :: Python :: 3.12
Classifier: Programming Language :: Python :: 3.13
Classifier: Programming Language :: Python :: 3.14
Requires-Dist: CoolProp (>=6.6.0,<7.0.0)
Requires-Dist: black (==22.12.0)
Requires-Dist: click (>=8.1.7,<9.0.0)
Requires-Dist: jsonschema (>=4.23.0,<5.0.0)
Requires-Dist: matplotlib (>=3.9.1,<4.0.0)
Requires-Dist: numpy (>=2.0.1,<3.0.0)
Requires-Dist: pandas (>=2.2.2,<3.0.0)
Requires-Dist: scipy (>=1.14.0,<2.0.0)
Requires-Dist: statsmodels (>=0.14.2,<0.15.0)
